zeclient/__init__.py
zeclient/http_client.py
zeclient/odata_client.py
zeclient/rest_client.py
zeclient/soap_client.py
zeclient/soap_proxy.py
zeclient/soap_util.py
zeclient/zema_auth.py
zeclient/zema_client.py
zeclient/oauth2/__init__.py
zeclient/oauth2/adfs_authorization_code.py
zeclient/oauth2/adfs_bearer_token.py
zeclient/oauth2/generic_resource_owner_password_flow.py
zeclient/oauth2/keycloak_resource_owner_password.py
zeclient/oauth2/oauth2_flow.py
zeclient/oauth2/okta_authorization_code.py
zeclient/oauth2/okta_resource_owner_password.py
zeclient/oauth2/ping_authorization_code.py
zeclient/oauth2/ping_resource_owner_password.py
zeclient-1.1.8.dist-info/LICENSE.txt
zeclient-1.1.8.dist-info/METADATA
zeclient-1.1.8.dist-info/WHEEL
zeclient-1.1.8.dist-info/top_level.txt
zeclient-1.1.8.dist-info/RECORD
