Metadata-Version: 2.1
Name: zeclient
Version: 1.1.8
Summary: Python APIs for ZE Web Services
Home-page: http://www.ze.com
Author: ZE
Author-email: ZE <support@ze.com>
License: Please refer to the ZEMA license
Requires-Python: >=3.5
License-File: LICENSE.txt
Requires-Dist: requests
Requires-Dist: lxml
Requires-Dist: dicttoxml
Requires-Dist: pandas
Requires-Dist: zeep
Requires-Dist: beautifulsoup4
Provides-Extra: test
Requires-Dist: pytest-cov; extra == "test"
Requires-Dist: pytest; extra == "test"
Requires-Dist: configparser; extra == "test"
Requires-Dist: numpy; extra == "test"
Requires-Dist: tabulate; extra == "test"
Requires-Dist: validate_email; extra == "test"
